webfsd
httpit-1.21.7.dist-info/RECORD
httpit-1.21.7.dist-info/WHEEL
httpit-1.21.7.dist-info/entry_points.txt
httpit-1.21.7.dist-info/top_level.txt
httpit-1.21.7.dist-info/METADATA
httpit-1.21.7.dist-info/licenses/LICENSE
fasthttp/webfsd
fasthttp/server.py
fasthttp/__init__.py
fasthttp/_webfsd.cpython-310-darwin.so
fasthttp/embedded.py
fasthttp/__main__.py
