Metadata-Version: 2.4
Name: httpit
Version: 1.21.7
Summary: Ultra-fast lightweight HTTP server
Home-page: https://github.com/yourusername/httpit
Author: Farshid Ashouri
Author-email: Farshid Ashouri <farshid@rodmena.co.uk>
Maintainer-email: Farshid Ashouri <farshid@rodmena.co.uk>
License: GPL-2.0
Project-URL: Homepage, https://github.com/rodmena-limited/fasthttp
Project-URL: Repository, https://github.com/rodmena-limited/fasthttp
Project-URL: Company, https://rodmena.co.uk
Project-URL: Issues, https://github.com/rodmena-limited/fasthttp/issues
Classifier: Development Status :: 4 - Beta
Classifier: Intended Audience :: Developers
Classifier: License :: OSI Approved :: GNU General Public License v2 (GPLv2)
Classifier: Operating System :: POSIX
Classifier: Operating System :: MacOS :: MacOS X
Classifier: Programming Language :: C
Classifier: Programming Language :: Python :: 3
Classifier: Programming Language :: Python :: 3.9
Classifier: Programming Language :: Python :: 3.10
Classifier: Programming Language :: Python :: 3.11
Classifier: Programming Language :: Python :: 3.12
Classifier: Programming Language :: Python :: 3.13
Classifier: Topic :: Internet :: WWW/HTTP :: HTTP Servers
Requires-Python: >=3.9
License-File: LICENSE
Requires-Dist: setuptools>=80.9.0
Dynamic: author
Dynamic: home-page
Dynamic: license-file
Dynamic: requires-python
